aggdirect_price_calculator/__init__.py
aggdirect_price_calculator-0.5.dist-info/LICENSE
aggdirect_price_calculator-0.5.dist-info/METADATA
aggdirect_price_calculator-0.5.dist-info/WHEEL
aggdirect_price_calculator-0.5.dist-info/top_level.txt
aggdirect_price_calculator-0.5.dist-info/RECORD
